LICENSE.txt
MANIFEST.in
README.rst
setup.cfg
setup.py
django_mojeid/__init__.py
django_mojeid/admin.py
django_mojeid/attribute_handlers.py
django_mojeid/auth.py
django_mojeid/errors.py
django_mojeid/exceptions.py
django_mojeid/models.py
django_mojeid/mojeid.py
django_mojeid/settings.py
django_mojeid/signals.py
django_mojeid/store.py
django_mojeid/urls.py
django_mojeid/views.py
django_mojeid.egg-info/PKG-INFO
django_mojeid.egg-info/SOURCES.txt
django_mojeid.egg-info/dependency_links.txt
django_mojeid.egg-info/requires.txt
django_mojeid.egg-info/top_level.txt
django_mojeid/locale/cs/LC_MESSAGES/django.mo
django_mojeid/locale/cs/LC_MESSAGES/django.po
django_mojeid/management/__init__.py
django_mojeid/management/commands/__init__.py
django_mojeid/management/commands/openid_cleanup.py
django_mojeid/static/mojeid/black_155x24.png
django_mojeid/static/mojeid/black_155x24_en.png
django_mojeid/static/mojeid/black_162x32.png
django_mojeid/static/mojeid/black_162x32_en.png
django_mojeid/static/mojeid/black_16x16.png
django_mojeid/static/mojeid/black_32x32.png
django_mojeid/static/mojeid/black_92x32.png
django_mojeid/static/mojeid/silver_155x24.png
django_mojeid/static/mojeid/silver_155x24_en.png
django_mojeid/static/mojeid/silver_162x32.png
django_mojeid/static/mojeid/silver_162x32_en.png
django_mojeid/static/mojeid/silver_16x16.png
django_mojeid/static/mojeid/silver_32x32.png
django_mojeid/static/mojeid/silver_92x32.png
django_mojeid/static/mojeid/zalozit_green_2D.png
django_mojeid/static/mojeid/zalozit_green_3D.png
django_mojeid/static/mojeid/zalozit_grey_2D.png
django_mojeid/static/mojeid/zalozit_grey_3D.png
django_mojeid/static/openid/openid-16x16.gif
django_mojeid/static/openid/openid-logo-wordmark.png
django_mojeid/templates/mojeid/_associate.html
django_mojeid/templates/mojeid/_login.html
django_mojeid/templates/mojeid/_register.html
django_mojeid/templates/openid/_associate.html
django_mojeid/templates/openid/_login.html
django_mojeid/templates/openid/associate.html
django_mojeid/templates/openid/failure.html
django_mojeid/templates/openid/login.html
django_mojeid/templates/openid/registration_form.html
django_mojeid/templates/openid/top.html
